thema/__init__.py
thema/config.py
thema/core.py
thema/thema.py
thema/utils.py
thema/expansion/__init__.py
thema/expansion/realtor.py
thema/expansion/utils.py
thema/multiverse/__init__.py
thema/multiverse/system/__init__.py
thema/multiverse/system/inner/__init__.py
thema/multiverse/system/inner/inner_utils.py
thema/multiverse/system/inner/moon.py
thema/multiverse/system/inner/planet.py
thema/multiverse/system/outer/__init__.py
thema/multiverse/system/outer/comet.py
thema/multiverse/system/outer/oort.py
thema/multiverse/system/outer/projectiles/__init__.py
thema/multiverse/system/outer/projectiles/pcaProj.py
thema/multiverse/system/outer/projectiles/tsneProj.py
thema/multiverse/universe/__init__.py
thema/multiverse/universe/galaxy.py
thema/multiverse/universe/geodesics.py
thema/multiverse/universe/star.py
thema/multiverse/universe/stars/__init__.py
thema/multiverse/universe/stars/gudhiStar.py
thema/multiverse/universe/stars/jmapStar.py
thema/multiverse/universe/stars/pyballStar.py
thema/multiverse/universe/utils/__init__.py
thema/multiverse/universe/utils/starFilters.py
thema/multiverse/universe/utils/starGraph.py
thema/multiverse/universe/utils/starHelpers.py
thema/multiverse/universe/utils/starSelectors.py
thema-0.1.4.dist-info/METADATA
thema-0.1.4.dist-info/WHEEL
thema-0.1.4.dist-info/licenses/LICENSE.md
thema-0.1.4.dist-info/RECORD
