Metadata-Version: 2.4
Name: thema
Version: 0.1.4
Summary: Topological Hyperparameter Evaluation and Mapping Algorithm, by Krv Labs
Author-email: Krv Labs <team@krv.ai>
License-File: LICENSE.md
Requires-Python: >=3.10
Requires-Dist: category-encoders>=2.8.1
Requires-Dist: curvature-filtrations>=0.1.2
Requires-Dist: gudhi>=3.11.0
Requires-Dist: hdbscan>=0.8.40
Requires-Dist: ipywidgets>=8.1.8
Requires-Dist: jupyter>=1.1.1
Requires-Dist: kmapper>=2.1.0
Requires-Dist: networkx>=3.4.2
Requires-Dist: numpy>=2.2.6
Requires-Dist: omegaconf>=2.3.0
Requires-Dist: pandas>=2.3.1
Requires-Dist: pyballmapper>=0.3.7
Requires-Dist: pyyaml>=6.0.2
Requires-Dist: scikit-learn>=1.7.1
Requires-Dist: tqdm>=4.67.1
Provides-Extra: dev
Requires-Dist: black>=25.9.0; extra == 'dev'
Requires-Dist: openpyxl>=3.1.5; extra == 'dev'
Requires-Dist: pytest-cov>=6.2.1; extra == 'dev'
Requires-Dist: pytest>=8.4.1; extra == 'dev'
Provides-Extra: docs
Requires-Dist: furo>=2025.7.19; extra == 'docs'
Requires-Dist: ipython>=8.37.0; extra == 'docs'
Requires-Dist: nbsphinx>=0.9.7; extra == 'docs'
Requires-Dist: sphinx-design>=0.6.1; extra == 'docs'
Requires-Dist: sphinx>=8.1.3; extra == 'docs'
Requires-Dist: sphinxcontrib-mermaid>=0.9.2; extra == 'docs'
